[{"TimeUTC":"2025-08-24 18:17:20","timestampInMs":1756059440447,"requestPath":"home-dathqrj4w-mushfiqplabons-projects.vercel.app/","requestMethod":"GET","requestQueryString":"","responseStatusCode":-1,"requestId":"5p5jz-1756059438308-3e6e5a393abf","requestUserAgent":"vercel-favicon/1.0","level":"error","environment":"production","branch":"main","vercelCache":"","type":"lambda","function":"/HomeSer/wsgi.py","host":"home-dathqrj4w-mushfiqplabons-projects.vercel.app","deploymentDomain":"home-dathqrj4w-mushfiqplabons-projects.vercel.app","deploymentId":"dpl_Dgrxau7271xodXcyFXkCS4YEuBPu","durationMs":-1,"region":"iad1","maxMemoryUsed":-1,"memorySize":-1,"message":"Traceback (most recent call last):\nFile \"/var/task/vc__handler__python.py\", line 218, in <module>\nif not issubclass(base, BaseHTTPRequestHandler):\n^^^^^^^^^^^^^^^^^^^^^^^^^^^^^^^^^^^^^^^^\nTypeError: issubclass() arg 1 must be a class\nPython process exited with exit status: 1. The logs above can help with debugging the issue.","projectId":"prj_ZVCfoJvVIliQNSjxDBESj7xnNIiZ","traceId":"","sessionId":"","invocationId":"01K3EMS38H9CYHXD7MB35BEYCT","instanceId":"","concurrency":-1},{"TimeUTC":"2025-08-24 18:17:18","timestampInMs":1756059438353,"requestPath":"home-dathqrj4w-mushfiqplabons-projects.vercel.app/","requestMethod":"GET","requestQueryString":"","responseStatusCode":500,"requestId":"5p5jz-1756059438308-3e6e5a393abf","requestUserAgent":"vercel-favicon/1.0","level":"error","environment":"production","branch":"main","vercelCache":"","type":"lambda","function":"/HomeSer/wsgi.py","host":"home-dathqrj4w-mushfiqplabons-projects.vercel.app","deploymentDomain":"home-dathqrj4w-mushfiqplabons-projects.vercel.app","deploymentId":"dpl_Dgrxau7271xodXcyFXkCS4YEuBPu","durationMs":2073,"region":"iad1","maxMemoryUsed":107,"memorySize":2048,"message":"","projectId":"prj_ZVCfoJvVIliQNSjxDBESj7xnNIiZ","traceId":"","sessionId":"","invocationId":"01K3EMS38H9CYHXD7MB35BEYCT","instanceId":"","concurrency":1}]